verbarius/__init__.py
verbarius/languages.py
verbarius/string_temps.py
verbarius/string_temps_ru.py
verbarius/string_temps_ua.py
verbarius/verbarius.py
verbarius-0.7.dist-info/LICENSE
verbarius-0.7.dist-info/METADATA
verbarius-0.7.dist-info/WHEEL
verbarius-0.7.dist-info/top_level.txt
verbarius-0.7.dist-info/RECORD
