Metadata-Version: 2.1
Name: verbarius
Version: 0.7
Summary: VerbariusRus
Home-page: https://github.com/k4m454k/Verbarius
Author: Vadim Apenko
Author-email: k4m454k@gmail.com
License: UNKNOWN
Platform: UNKNOWN
Classifier: Programming Language :: Python :: 3.8
Classifier: License :: OSI Approved :: MIT License
Classifier: Operating System :: OS Independent
Requires-Python: >=3.6
